logto_admin/__init__.py
logto_admin/api/__init__.py
logto_admin/api/applications/__init__.py
logto_admin/api/applications/delete_api_applications_application_id_roles_role_id.py
logto_admin/api/applications/delete_api_applications_application_id_user_consent_scopes_scope_type_scope_id.py
logto_admin/api/applications/delete_api_applications_id.py
logto_admin/api/applications/delete_api_applications_id_protected_app_metadata_custom_domains_domain.py
logto_admin/api/applications/delete_api_applications_id_users_user_id_consent_organizations_organization_id.py
logto_admin/api/applications/get_api_applications.py
logto_admin/api/applications/get_api_applications_application_id_roles.py
logto_admin/api/applications/get_api_applications_application_id_sign_in_experience.py
logto_admin/api/applications/get_api_applications_application_id_user_consent_scopes.py
logto_admin/api/applications/get_api_applications_id.py
logto_admin/api/applications/get_api_applications_id_protected_app_metadata_custom_domains.py
logto_admin/api/applications/get_api_applications_id_users_user_id_consent_organizations.py
logto_admin/api/applications/patch_api_applications_id.py
logto_admin/api/applications/post_api_applications.py
logto_admin/api/applications/post_api_applications_application_id_roles.py
logto_admin/api/applications/post_api_applications_application_id_user_consent_scopes.py
logto_admin/api/applications/post_api_applications_id_protected_app_metadata_custom_domains.py
logto_admin/api/applications/post_api_applications_id_users_user_id_consent_organizations.py
logto_admin/api/applications/put_api_applications_application_id_roles.py
logto_admin/api/applications/put_api_applications_application_id_sign_in_experience.py
logto_admin/api/applications/put_api_applications_id_users_user_id_consent_organizations.py
logto_admin/api/audit_logs/__init__.py
logto_admin/api/audit_logs/get_api_logs.py
logto_admin/api/audit_logs/get_api_logs_id.py
logto_admin/api/authn/__init__.py
logto_admin-1.0.0.dist-info/LICENSE
logto_admin-1.0.0.dist-info/METADATA
logto_admin-1.0.0.dist-info/WHEEL
logto_admin-1.0.0.dist-info/RECORD
