Metadata-Version: 2.1
Name: logto-admin
Version: 1.0.0
Summary: Python client for Logto Management API
Home-page: https://github.com/ysemennikov/py-logto-admin
License: MIT
Author: Iaroslav Semennikov
Author-email: ysmnnkv@gmail.com
Requires-Python: >=3.8,<4.0
Classifier: License :: OSI Approved :: MIT License
Classifier: Programming Language :: Python :: 3
Classifier: Programming Language :: Python :: 3.8
Classifier: Programming Language :: Python :: 3.9
Classifier: Programming Language :: Python :: 3.10
Classifier: Programming Language :: Python :: 3.11
Classifier: Programming Language :: Python :: 3.12
Requires-Dist: attrs (>=21.3.0)
Requires-Dist: httpx (>=0.20.0,<0.28.0)
Requires-Dist: python-dateutil (>=2.8.0,<3.0.0)
Project-URL: Documentation, https://github.com/ysemennikov/py-logto-admin#logto-admin
Project-URL: Repository, https://github.com/ysemennikov/py-logto-admin
